{
  "images": [
    {
      "previewImageSrc": "https://apibackend.megapc.tn/uploads/gallerie/1714382006890.webp",
      "thumbnailImageSrc": "https://apibackend.megapc.tn/uploads/gallerie/1714382006890.webp",
      "imgBlur": "data:image/png;base64,iVBORw0KGgoAAAANSUhEUgAAAAQAAAAECAIAAAAmkwkpAAAACXBIWXMAAAPoAAAD6AG1e1JrAAAANUlEQVQImWO4dOny4UNH9+3df+z4cQY/P38ZaTkGBiZlZVWGAwcOrF69evHipdu2bWP4jwQA0gIfP1LwANgAAAAASUVORK5CYII="
    },
    {
      "previewImageSrc": "https://apibackend.megapc.tn/uploads/gallerie/1714382006893.webp",
      "thumbnailImageSrc": "https://apibackend.megapc.tn/uploads/gallerie/1714382006893.webp",
      "imgBlur": "data:image/png;base64,iVBORw0KGgoAAAANSUhEUgAAAAQAAAAECAIAAAAmkwkpAAAACXBIWXMAAAPoAAAD6AG1e1JrAAAAO0lEQVQImWP4Dwb//v37//8/w40bN2fMmHnnzp1nz54x+Pj4MDCwysjIWVhYMty9e3fZsmWBgYENDQ0Arxwebi4daXEAAAAASUVORK5CYII="
    },
    {
      "previewImageSrc": "https://apibackend.megapc.tn/uploads/gallerie/1714382006896.webp",
      "thumbnailImageSrc": "https://apibackend.megapc.tn/uploads/gallerie/1714382006896.webp",
      "imgBlur": "data:image/png;base64,iVBORw0KGgoAAAANSUhEUgAAAAQAAAAECAIAAAAmkwkpAAAACXBIWXMAAAPoAAAD6AG1e1JrAAAANUlEQVQImWP4jwQYNm3avH79pqSk5Dlz5jEEB4eoqqoxMDBpamoynD179tChA/v27Tt8+DAAbwQeLscpahUAAAAASUVORK5CYII="
    }
  ],
  "_id": "662f63d4f0d88c8c60e288f7",
  "sku": "C11CF40401",
  "mpn": "C11CF40401",
  "titleSeo": "",
  "ratingValue": "4",
  "reviewCount": "22",
  "priceValidUntil": "2023-09-08",
  "referenceInterne": "C11CF40401",
  "title": "IMPRIMANTE MATRICIELLE À IMPACT EPSON LQ-2090II",
  "title_fr": "IMPRIMANTE MATRICIELLE À IMPACT EPSON LQ-2090II",
  "description_fr": "",
  "miniDescription_fr": "<ul>\n\t<li><span style=\"font-size:22px\">Imprimante matricielle &agrave; impact 24 aiguilles, 136 colonnes</span></li>\n\t<li><span style=\"font-size:22px\">Interface USB</span></li>\n\t<li><span style=\"font-size:22px\">Grande vitesse d&#39;impression 550 caract&egrave;res par seconde &agrave; 10 caract&egrave;res par pouce</span></li>\n\t<li><span style=\"font-size:22px\">Epaisseur du papier des feuilles de base pour &eacute;tiquettes 0,16 mm - 0,19 mm</span></li>\n\t<li><span style=\"font-size:22px\">Epaisseur du papier en continu 0,12 mm - 0,46 mm</span></li>\n\t<li><span style=\"font-size:22px\">Dimensions 612&lrm; x 375 x 177 mm</span></li>\n</ul>\n",
  "notreSelection": true,
  "marque": {
    "_id": "658d34c652b5a275b6d678f1",
    "titre": "EPSON",
    "update_date": "2023-12-28T08:41:42.659Z",
    "create_date": "2023-12-28T08:41:42.000Z",
    "__v": 0,
    "targetGiga": true,
    "targetMega": true
  },
  "categorie": {
    "_id": "5f60ba4f01f417289807e75b",
    "order": 19,
    "titre": "IMPRESSION",
    "__v": 0,
    "urlPhoto2": "/uploads/categorie/1715428998314.webp",
    "create_date": "2020-09-15T12:57:51.000Z",
    "update_date": "2025-04-28T10:32:54.398Z",
    "visible": true,
    "targetGiga": true,
    "targetMega": true,
    "targetMobile": false,
    "urlPhoto": "/uploads/categorie/1715429007654.webp"
  },
  "filscateg": null,
  "attributes": [],
  "tag": [],
  "compatibility": [],
  "nFilsCategs": [
    "662f6336f0d88c8c60e288b5"
  ],
  "lien": "C11CF40401",
  "gallerie": {
    "_id": "662f64aaf0d88c8c60e33287",
    "titre": "IMPRIMANTE MATRICIELLE À IMPACT EPSON LQ-2090II",
    "urlPhoto": [
      "/uploads/gallerie/1714382006890.webp",
      "/uploads/gallerie/1714382006893.webp",
      "/uploads/gallerie/1714382006896.webp"
    ],
    "targetMega": true,
    "targetGiga": true,
    "update_date": "2024-04-29T09:13:27.036Z",
    "create_date": "2024-04-29T09:13:14.000Z",
    "__v": 1
  },
  "visibleHorsStock": false,
  "checkStockWhenPurchased": true,
  "visible": true,
  "facilite": false,
  "devis": false,
  "enPromo": false,
  "commande48H": true,
  "enArrivage": false,
  "new": true,
  "vue": 2275,
  "price": 1889,
  "tagsSearch": [
    "IMPRESSION",
    "IMPRIMANTE",
    "EPSON",
    "IMPRIMANTE MATRICIELLE"
  ],
  "stock": 40,
  "displayForPublic": true,
  "create_date": "2023-09-28T14:26:31.485Z",
  "update_date": "2025-10-22T18:55:01.832Z",
  "ccpu": [],
  "cwebCam": [],
  "cgpu": [],
  "ccase": [],
  "cram": [],
  "ccpuColler": [],
  "cventilateur": [],
  "ccarteMere": [],
  "calim": [],
  "chdd": [],
  "cssd": [],
  "cheadphone": [],
  "ccarteReseau": [],
  "cmonitor": [],
  "ckeyboard": [],
  "cmouse": [],
  "cmousepad": [],
  "cmousekeys": [],
  "cprinter": [],
  "cnvme": [],
  "cwindows": [],
  "cjeux": [],
  "productpriv": false,
  "specialproduct": false,
  "targetMega": true,
  "targetGiga": true,
  "targetMobile": true,
  "__v": 0
}