{
  "images": [
    {
      "previewImageSrc": "https://apibackend.megapc.tn/uploads/gallerie/1725111857208.webp",
      "thumbnailImageSrc": "https://apibackend.megapc.tn/uploads/gallerie/1725111857208.webp",
      "imgBlur": "data:image/png;base64,iVBORw0KGgoAAAANSUhEUgAAAAQAAAAECAIAAAAmkwkpAAAACXBIWXMAAAPoAAAD6AG1e1JrAAAAP0lEQVQImQE0AMv/AP///+zs69rd47+2kQDr7O4ZEAVfZmni7vUAvb2/EAoHDQACqquuAKOjo5aXmJubm7KxskORHUdabG/UAAAAAElFTkSuQmCC"
    },
    {
      "previewImageSrc": "https://apibackend.megapc.tn/uploads/gallerie/1725111857210.webp",
      "thumbnailImageSrc": "https://apibackend.megapc.tn/uploads/gallerie/1725111857210.webp",
      "imgBlur": "data:image/png;base64,iVBORw0KGgoAAAANSUhEUgAAAAQAAAAECAIAAAAmkwkpAAAACXBIWXMAAAPoAAAD6AG1e1JrAAAANklEQVQImWP4+vXrXxhgmDd3bkCA/5//IMBw6dIlVgaGnJz8J0+eMvz9+/fDh4+PHj36+vUrAO/tJj+AkwOpAAAAAElFTkSuQmCC"
    },
    {
      "previewImageSrc": "https://apibackend.megapc.tn/uploads/gallerie/1725111860986.webp",
      "thumbnailImageSrc": "https://apibackend.megapc.tn/uploads/gallerie/1725111860986.webp",
      "imgBlur": "data:image/png;base64,iVBORw0KGgoAAAANSUhEUgAAAAQAAAAECAIAAAAmkwkpAAAACXBIWXMAAAPoAAAD6AG1e1JrAAAAPElEQVQImQXBwQmAQBADwMWffSoIh90c+PLai2kgj8ASZypJdwOwXbbP4xrjTlLvWlvtcz4kSxLwkZT0A95xJYqnfB5RAAAAAElFTkSuQmCC"
    },
    {
      "previewImageSrc": "https://apibackend.megapc.tn/uploads/gallerie/1725111860987.webp",
      "thumbnailImageSrc": "https://apibackend.megapc.tn/uploads/gallerie/1725111860987.webp",
      "imgBlur": "data:image/png;base64,iVBORw0KGgoAAAANSUhEUgAAAAQAAAAECAIAAAAmkwkpAAAACXBIWXMAAAPoAAAD6AG1e1JrAAAAPElEQVQImWP48+fP69dv/v79+///f4b////39vbHRMV9+/aN4f3794sWLWZk4FiwYBHDz58/X4DB9+8/APz/JidPaIxNAAAAAElFTkSuQmCC"
    }
  ],
  "_id": "66bf6f8da3e5f93b2750a1cb",
  "sku": "N3002PVNB3520EMEA01-UBU",
  "mpn": "N3002PVNB3520EMEA01-UBU",
  "titleSeo": "PC PORTABLE Dell Vostro 3520 | 15.6\" | i5-1235U | 8GB RAM | 512GB SSD | MEGA ",
  "desciprtionSeo": "PC PORTABLE Dell Vostro 3520 | 15.6\" | i5-1235U | 8GB RAM | 512GB SSD | MEGA ",
  "ratingValue": "4.7",
  "reviewCount": "45",
  "priceValidUntil": "2026-09-08 ",
  "referenceInterne": "N3002PVNB3520EMEA01-UBU",
  "title": "Dell Vostro 3520 | 15.6\" | i5-1235U | 8GB RAM | 512GB SSD",
  "title_fr": "Dell Vostro 3520 | 15.6\" | i5-1235U | 8GB RAM | 512GB SSD",
  "description_fr": "<h2>Dell Vostro 3520 | 15.6&quot; | i5-1235U | 8GB RAM | 512GB SSD</h2>\n\n<hr />\n<p><span style=\"font-size:22px\">Le Dell Vostro 3520 est un ordinateur portable de 15,6 pouces con&ccedil;u pour les professionnels recherchant un outil performant pour les t&acirc;ches quotidiennes. Il est &eacute;quip&eacute; d&#39;un &eacute;cran Full HD avec un taux de rafra&icirc;chissement de 120 Hz, offrant une exp&eacute;rience visuelle fluide. Sous le capot, il embarque un processeur Intel Core i5-1235U, dot&eacute; de deux c&oelig;urs de performance pouvant atteindre une fr&eacute;quence turbo de 4,4 GHz, ce qui assure une bonne r&eacute;activit&eacute; pour les applications de bureautique et de gestion. Le chipset graphique Intel UHD Graphics est int&eacute;gr&eacute;, id&eacute;al pour les t&acirc;ches graphiques l&eacute;g&egrave;res. Ce mod&egrave;le est livr&eacute; avec 8GB de RAM DDR4, ce qui est suffisant pour le multit&acirc;che de base, mais une mise &agrave; niveau pourrait &ecirc;tre n&eacute;cessaire pour des performances plus exigeantes. En termes de stockage, le Vostro 3520 dispose d&#39;un SSD NVMe de 512GB, garantissant des temps de d&eacute;marrage rapides et une gestion efficace des fichiers. Enfin, il fonctionne sous Windows 11, offrant une interface utilisateur moderne et des fonctionnalit&eacute;s avanc&eacute;es pour am&eacute;liorer la productivit&eacute;.</span></p>\n",
  "miniDescription_fr": "<ul>\n\t<li><span style=\"font-size:22px\">Afficheur : 15.6&Prime; FHD 120 Hz</span></li>\n\t<li><span style=\"font-size:22px\">Processeur : Intel i5-1235U (2 Performance-Cores 4.4 GHz Turbo&nbsp; )</span></li>\n\t<li><span style=\"font-size:22px\">Chipset Graphique : Intel UHD Graphics</span></li>\n\t<li><span style=\"font-size:22px\">Ram : 8GB DDR4</span></li>\n\t<li><span style=\"font-size:22px\">Stockage : 512 NVMe SSD</span></li>\n\t<li><span style=\"font-size:22px\">Syst&egrave;me d&rsquo;exploitation :&nbsp; UBUNTU</span></li>\n</ul>\n",
  "notreSelection": true,
  "marque": {
    "_id": "5ea2359ca4815052c4d1a427",
    "titre": "DELL",
    "__v": 0,
    "urlPhoto": "/uploads/marque/1604326347940.webp",
    "targetGiga": true,
    "targetMega": true,
    "create_date": "2020-04-24T00:41:00.000Z"
  },
  "categorie": {
    "_id": "61bb23c7a14a1b547a40a936",
    "titre": "PC PORTABLE",
    "order": 2,
    "visible": true,
    "update_date": "2025-04-28T10:29:51.496Z",
    "create_date": "2021-12-16T11:32:23.000Z",
    "__v": 0,
    "urlPhoto2": "/uploads/categorie/1639654349693.png",
    "reference": "externe",
    "targetGiga": true,
    "targetMega": true,
    "targetMobile": true
  },
  "filscateg": {
    "children": [],
    "_id": "61bb3568a14a1b547a472917",
    "titre": "PC PORTABLE PRO",
    "visible": true,
    "order": 1,
    "categorie": "61bb23c7a14a1b547a40a936",
    "update_date": "2021-12-18T09:38:31.859Z",
    "create_date": "2021-12-16T12:47:36.000Z",
    "__v": 0,
    "urlPhoto2": "/uploads/souscateg/1639752903267.webp",
    "marge": 1.1,
    "tva": 1.07,
    "targetGiga": true,
    "targetMega": true
  },
  "attributes": [],
  "tag": [],
  "compatibility": [],
  "nFilsCategs": [
    "61bb3568a14a1b547a472917"
  ],
  "lien": "Dell-Vostro-3520-15-6-i5-1235U-8GB-RAM-512GB-SSD",
  "gallerie": {
    "_id": "66d31e0eb57966b0a036f15b",
    "titre": "V3520-I5",
    "urlPhoto": [
      "/uploads/gallerie/1725111857208.webp",
      "/uploads/gallerie/1725111857210.webp",
      "/uploads/gallerie/1725111860986.webp",
      "/uploads/gallerie/1725111860987.webp"
    ],
    "targetMega": true,
    "targetGiga": true,
    "targetMobile": true,
    "update_date": "2024-08-31T13:44:21.103Z",
    "create_date": "2024-08-31T13:43:42.000Z",
    "__v": 2
  },
  "visibleHorsStock": false,
  "checkStockWhenPurchased": true,
  "visible": true,
  "facilite": false,
  "devis": false,
  "enPromo": false,
  "commande48H": false,
  "enArrivage": false,
  "new": true,
  "vue": 1572,
  "price": 1425,
  "tagsSearch": [
    "DELL",
    "MEGAPC",
    "PC PORTABLE",
    "PC PORTABLE ÉCONOMIQUE - الفئة أقتصادي",
    "PC PORTABLE PRO",
    "N3002PVNB3520EMEA01-UBU"
  ],
  "stock": 0,
  "displayForPublic": true,
  "create_date": "2024-08-16T15:26:05.839Z",
  "update_date": "2025-10-31T21:21:47.042Z",
  "ccpu": [],
  "cwebCam": [],
  "cgpu": [],
  "ccase": [],
  "cram": [],
  "ccpuColler": [],
  "cventilateur": [],
  "ccarteMere": [],
  "calim": [],
  "chdd": [],
  "cssd": [],
  "cheadphone": [],
  "ccarteReseau": [],
  "cmonitor": [],
  "ckeyboard": [],
  "cmouse": [],
  "cmousepad": [],
  "cmousekeys": [],
  "cprinter": [],
  "cnvme": [],
  "cwindows": [],
  "cjeux": [],
  "productpriv": false,
  "specialproduct": false,
  "targetMega": true,
  "targetGiga": true,
  "targetMobile": true,
  "__v": 0
}