{
  "images": [
    {
      "previewImageSrc": "https://apibackend.megapc.tn/uploads/gallerie/1729079818416.jpg",
      "thumbnailImageSrc": "https://apibackend.megapc.tn/uploads/gallerie/1729079818416.jpg",
      "imgBlur": "data:image/png;base64,iVBORw0KGgoAAAANSUhEUgAAAAQAAAAECAIAAAAmkwkpAAAACXBIWXMAAC4jAAAuIwF4pT92AAAAOElEQVQImRXHsREAIQgAQcYetQQ1hZq0HRL6oACS+3ezFeCcq6qAVJWZ9T5e3F2kzbVfgMyMiD8fd7wjV35wKAAAAAAASUVORK5CYII="
    },
    {
      "previewImageSrc": "https://apibackend.megapc.tn/uploads/gallerie/1729079839355.jpg",
      "thumbnailImageSrc": "https://apibackend.megapc.tn/uploads/gallerie/1729079839355.jpg",
      "imgBlur": "data:image/png;base64,iVBORw0KGgoAAAANSUhEUgAAAAQAAAAECAIAAAAmkwkpAAAACXBIWXMAAC4jAAAuIwF4pT92AAAAP0lEQVQImQE0AMv/AOTl5/X09fj4+Pf3+ACTk5ozPU9haXVOT1wA7e3uTVRiAAAbdneAAP///+Li5EhIVVhcZkunHQscU9nBAAAAAElFTkSuQmCC"
    },
    {
      "previewImageSrc": "https://apibackend.megapc.tn/uploads/gallerie/1729080152548.jpg",
      "thumbnailImageSrc": "https://apibackend.megapc.tn/uploads/gallerie/1729080152548.jpg",
      "imgBlur": "data:image/png;base64,iVBORw0KGgoAAAANSUhEUgAAAAQAAAAECAIAAAAmkwkpAAAACXBIWXMAAC4jAAAuIwF4pT92AAAAOElEQVQImRXHsREAIQgAQcYetQQ1hZq0HRL6oACS+3ezFeCcq6qAVJWZ9T5e3F2kzbVfgMyMiD8fd7wjV35wKAAAAAAASUVORK5CYII="
    }
  ],
  "_id": "670faa5499de58d4f6f24fdf",
  "sku": "PW-U2HB",
  "mpn": "PW-U2HB",
  "titleSeo": "LIAN LI USB 2.0 1-TO-3 HUB PW-U2HB | MEGA TUNISIE",
  "desciprtionSeo": "LIAN LI USB 2.0 1-TO-3 HUB PW-U2HB Modèle : PW-U2HB (Noir) Nombre de ports : 1 vers 3 (USB 2.0) Dimensions du câble mâle : 140 mm Dimensions des câbles femelles : 3 × 140 mm Dimensions du hub : 60 mm (L) × 39 mm (l) × 11 mm (H) | MEGA TUNISIE",
  "ratingValue": "4",
  "reviewCount": "45",
  "priceValidUntil": "2028-09-08",
  "referenceInterne": "PW-U2HB",
  "title": "LIAN LI USB 2.0 1-TO-3 HUB PW-U2HB",
  "title_fr": "LIAN LI USB 2.0 1-TO-3 HUB PW-U2HB",
  "description_fr": "<h2>LIAN LI USB 2.0 1-TO-3 HUB PW-U2HB</h2>\n\n<hr />\n<p><span style=\"font-size:22px\">Le Lian Li USB 2.0 1-to-3 HUB est un r&eacute;partiteur pratique con&ccedil;u pour &eacute;tendre une seule connexion USB 2.0 en trois ports suppl&eacute;mentaires. Ce hub compact, de couleur noire, est id&eacute;al pour connecter plusieurs p&eacute;riph&eacute;riques USB tout en &eacute;conomisant de l&#39;espace. Il est &eacute;quip&eacute; d&#39;un c&acirc;ble m&acirc;le de 140 mm et de trois c&acirc;bles femelles de la m&ecirc;me longueur, offrant une flexibilit&eacute; d&#39;installation. Le bo&icirc;tier du hub mesure 60 mm de longueur, 39 mm de largeur, et 11 mm de hauteur, ce qui en fait un accessoire discret et facile &agrave; int&eacute;grer dans n&#39;importe quel setup.</span></p>\n",
  "miniDescription_fr": "<ul>\n\t<li><span style=\"font-size:22px\"><strong>Mod&egrave;le</strong> : PW-U2HB (Noir)</span></li>\n\t<li><span style=\"font-size:22px\"><strong>Nombre de ports</strong> : 1 vers 3 (USB 2.0)</span></li>\n\t<li><span style=\"font-size:22px\"><strong>Dimensions du c&acirc;ble m&acirc;le</strong> : 140 mm</span></li>\n\t<li><span style=\"font-size:22px\"><strong>Dimensions des c&acirc;bles femelles</strong> : 3 &times; 140 mm</span></li>\n\t<li><span style=\"font-size:22px\"><strong>Dimensions du hub</strong> : 60 mm (L) &times; 39 mm (l) &times; 11 mm (H)</span></li>\n\t<li><span style=\"font-size:22px\"><strong>Couleur</strong> : Noir</span></li>\n</ul>\n",
  "notreSelection": true,
  "marque": {
    "_id": "5fd09f226c4a9703cc6cba3c",
    "titre": "LIAN-LI",
    "description": "LIAN-LI",
    "__v": 0,
    "urlPhoto": "/uploads/marque/1607507773241.webp",
    "targetGiga": true,
    "targetMega": true,
    "create_date": "2020-12-09T09:55:46.000Z"
  },
  "categorie": {
    "_id": "5f622c11fc1c8856d8a99784",
    "order": 3,
    "titre": "COMPOSANTS",
    "__v": 0,
    "urlPhoto": "/uploads/categorie/1602162244337.jpg",
    "urlPhoto2": "/uploads/categorie/1620205168544.webp",
    "description": "<h1>Composants&nbsp;pc : Processeur, Carte Graphique, Carte Mere...<br></h1><p>MEGA PC les spécialistes du gaming en Tunisie - Ordinateurs de bureau, Pc gamer, PC Portable, <strong>PC pour Gaming</strong>,. <br>Comparez et achetez votre Composant PC au meilleur prix sur Megapc.tn ! <strong>Processeurs</strong>, <strong>Carte mère</strong>, <strong>Cartes graphiques</strong>, <strong>Boîtiers PC</strong> &amp; <strong>alimentation</strong> PC Gamer.<br>Avec MegaPc, vous trouverez tout ce dont vous avez besoin, de vos composants pc aux périphériques externes avec un large choix de <a href=\"https://megapc.tn/shop/ORDINATEURS/PC%20GAMER\"><strong>PCs Gamer</strong></a> assemblé sur mesure.</p>",
    "create_date": "2020-09-16T15:15:29.000Z",
    "update_date": "2025-04-28T10:30:01.771Z",
    "visible": true,
    "targetGiga": true,
    "targetMega": true,
    "targetMobile": true
  },
  "filscateg": {
    "children": [],
    "_id": "5ea232b7a4815052c4d1a41b",
    "titre": "CARTE GRAPHIQUE",
    "categorie": "5f622c11fc1c8856d8a99784",
    "__v": 0,
    "urlPhoto2": "/uploads/souscateg/1620205659932.webp",
    "order": 4,
    "descriptionSEO": "<p>Carte graphique pc Gamer , ordinateur bureau Nvidia RTX 3060Ti, RTX 3060, RTX 3070, RTX 3080, RTX 3090 GIGABYTE, ASUS, MSI, PNY GTX. Prix Tunisie. </p>",
    "titreSEO": "carte graphique Tunisie | Carte graphique pc gamer Nvidia RTX - MegaPC",
    "create_date": "2020-04-24T00:28:39.000Z",
    "reference": "GPU",
    "update_date": "2021-10-15T15:28:01.148Z",
    "visible": true,
    "targetGiga": true,
    "targetMega": true
  },
  "attributes": [],
  "tag": [],
  "compatibility": [],
  "nFilsCategs": [
    "5ea232b7a4815052c4d1a41b"
  ],
  "lien": "LIAN-LI-USB-2.0-1-TO-3-HUB-PW-U2HB",
  "gallerie": {
    "_id": "670fa9fa99de58d4f6f24fa2",
    "titre": "LIAN LI USB 2.0 1-TO-3 HUB (MODÈLE PW-U2HB)",
    "urlPhoto": [
      "/uploads/gallerie/1729079818416.jpg",
      "/uploads/gallerie/1729079839355.jpg",
      "/uploads/gallerie/1729080152548.jpg"
    ],
    "targetMega": true,
    "targetGiga": true,
    "targetMobile": true,
    "update_date": "2024-10-16T12:03:09.096Z",
    "create_date": "2024-10-16T11:56:42.000Z",
    "__v": 6
  },
  "visibleHorsStock": false,
  "checkStockWhenPurchased": false,
  "visible": false,
  "facilite": false,
  "devis": false,
  "enPromo": false,
  "commande48H": false,
  "enArrivage": false,
  "new": true,
  "vue": 1397,
  "price": 150,
  "tagsSearch": [
    "LIAN-LI",
    "COMPOSANTS",
    "CARTE GRAPHIQUE"
  ],
  "stock": 0,
  "displayForPublic": false,
  "create_date": "2024-10-16T11:58:12.767Z",
  "update_date": "2025-10-24T12:37:53.826Z",
  "ccpu": [],
  "cwebCam": [],
  "cgpu": [],
  "ccase": [],
  "cram": [],
  "ccpuColler": [],
  "cventilateur": [],
  "ccarteMere": [],
  "calim": [],
  "chdd": [],
  "cssd": [],
  "cheadphone": [],
  "ccarteReseau": [],
  "cmonitor": [],
  "ckeyboard": [],
  "cmouse": [],
  "cmousepad": [],
  "cmousekeys": [],
  "cprinter": [],
  "cnvme": [],
  "cwindows": [],
  "cjeux": [],
  "productpriv": false,
  "specialproduct": false,
  "targetMega": true,
  "targetGiga": true,
  "targetMobile": true,
  "__v": 0
}