{
  "images": [
    {
      "previewImageSrc": "https://apibackend.megapc.tn/uploads/gallerie/1724316637296.webp",
      "thumbnailImageSrc": "https://apibackend.megapc.tn/uploads/gallerie/1724316637296.webp",
      "imgBlur": "data:image/png;base64,iVBORw0KGgoAAAANSUhEUgAAAAQAAAAECAIAAAAmkwkpAAAACXBIWXMAAAPoAAAD6AG1e1JrAAAAMUlEQVQImWP4//9/WExCXWPr////Gf7//y8jKxsaFgblKCrKxcfGQDkMDAwODg5ABgAsvR4OxXJvVQAAAABJRU5ErkJggg=="
    }
  ],
  "_id": "66c6fc9e72b73402591a770c",
  "sku": "GR11-3K",
  "mpn": "GR11-3K",
  "titleSeo": "ONDULEUR ON LINE KEBOS 3000VA GR11-3K | MEGA TUNISIE",
  "desciprtionSeo": "ONDULEUR ON LINE KEBOS 3000VA GR11-3K Puissance : 3000VA / 2700W - Plage de tension d'entrée :110-300 VAC - Plage de fréquence :  40-70 Hz -  | MEGA TUNISIE",
  "ratingValue": "4",
  "reviewCount": "45",
  "priceValidUntil": "2024-09-08 ",
  "referenceInterne": "GR11-3K",
  "title": "ONDULEUR ON LINE KEBOS 3000VA GR11-3K",
  "title_fr": "ONDULEUR ON LINE KEBOS 3000VA GR11-3K",
  "description_fr": "<h2>ONDULEUR ON LINE KEBOS 3000VA GR11-3K</h2>\n\n<hr />\n<p><span style=\"font-size:22px\">L&#39;ONDULEUR ON LINE KEBOS 3000VA GR11-3K offre une puissance de 3000VA / 2700W. La plage de tension d&#39;entr&eacute;e varie entre 110 et 300 VAC, et la plage de fr&eacute;quence entre 40 et 70 Hz. La tension de sortie est r&eacute;glable entre 200, 208, 220, 230, et 240 VAC avec une pr&eacute;cision de &plusmn;1%. La plage de fr&eacute;quence synchronis&eacute;e est de 47-53 Hz ou 57-63 Hz. Le temps de transfert est de 0ms. Il utilise une batterie de 12V 9AH (6 pi&egrave;ces). Garantie de 1 an.</span></p>\n",
  "miniDescription_fr": "<ul>\n\t<li><span style=\"font-size:22px\"><strong>Puissance :</strong> 3000VA / 2700W</span></li>\n\t<li><span style=\"font-size:22px\"><strong>Plage de tension d&#39;entr&eacute;e :</strong> 110-300 VAC</span></li>\n\t<li><span style=\"font-size:22px\"><strong>Plage de fr&eacute;quence d&#39;entr&eacute;e :</strong> 40-70 Hz</span></li>\n\t<li><span style=\"font-size:22px\"><strong>Tension de sortie :</strong> 200/208/220/230/240 VAC &plusmn;1%</span></li>\n\t<li><span style=\"font-size:22px\"><strong>Plage de fr&eacute;quence (synchronis&eacute;e) :</strong> 47-53 Hz ou 57-63 Hz</span></li>\n\t<li><span style=\"font-size:22px\"><strong>Temps de transfert :</strong> 0ms</span></li>\n\t<li><span style=\"font-size:22px\"><strong>Batterie :</strong> 12V 9AH (6 pi&egrave;ces)</span></li>\n\t<li><span style=\"font-size:22px\"><strong>Garantie :</strong> 1 an</span></li>\n</ul>\n",
  "notreSelection": true,
  "marque": {
    "_id": "66c5c58f5343d3207937a157",
    "titre": "KEBOS",
    "visible": true,
    "targetMega": true,
    "targetGiga": true,
    "targetMobile": true,
    "update_date": "2024-08-21T10:46:39.498Z",
    "create_date": "2024-08-21T10:46:39.000Z",
    "__v": 0
  },
  "categorie": {
    "_id": "5ea231f9a4815052c4d1a414",
    "order": 17,
    "titre": "ONDULEUR",
    "__v": 0,
    "urlPhoto2": "/uploads/categorie/1715593624308.webp",
    "create_date": "2020-04-24T00:25:29.000Z",
    "update_date": "2025-04-28T10:32:32.792Z",
    "visible": true,
    "targetGiga": true,
    "targetMega": true,
    "targetMobile": false,
    "urlPhoto": "/uploads/categorie/1715593631484.webp"
  },
  "filscateg": {
    "children": [],
    "_id": "60103b65821a45a8fb5f0071",
    "order": 2,
    "titre": "ONDULEURS ON-LINE",
    "categorie": "5ea231f9a4815052c4d1a414",
    "__v": 0,
    "urlPhoto2": "/uploads/souscateg/1715770528464.webp",
    "create_date": "2021-01-26T15:55:17.000Z",
    "reference": "ONDULEURS ON-LINE",
    "update_date": "2024-05-15T10:55:28.582Z",
    "visible": true,
    "targetGiga": true,
    "targetMega": true,
    "targetMobile": true
  },
  "attributes": [],
  "tag": [],
  "compatibility": [],
  "nFilsCategs": [
    "60103b65821a45a8fb5f0071"
  ],
  "lien": "ONDULEUR-ON-LINE-KEBOS-3000VA-GR11-3K",
  "gallerie": {
    "_id": "66c6fbd272b73402591a76bc",
    "titre": "ONDULEUR ON LINE KEBOS 3000VA GR11-3K",
    "urlPhoto": [
      "/uploads/gallerie/1724316637296.webp"
    ],
    "targetMega": true,
    "targetGiga": true,
    "targetMobile": true,
    "update_date": "2024-08-22T08:50:37.414Z",
    "create_date": "2024-08-22T08:50:26.000Z",
    "__v": 1
  },
  "visibleHorsStock": false,
  "checkStockWhenPurchased": true,
  "visible": true,
  "facilite": false,
  "devis": false,
  "enPromo": false,
  "commande48H": false,
  "enArrivage": false,
  "new": true,
  "vue": 393,
  "price": 2569,
  "tagsSearch": [
    "KEBOS",
    "ONDULEUR",
    "ONDULEURS ON-LINE"
  ],
  "stock": 10,
  "displayForPublic": true,
  "create_date": "2024-08-22T08:53:50.504Z",
  "update_date": "2025-10-31T10:54:30.916Z",
  "ccpu": [],
  "cwebCam": [],
  "cgpu": [],
  "ccase": [],
  "cram": [],
  "ccpuColler": [],
  "cventilateur": [],
  "ccarteMere": [],
  "calim": [],
  "chdd": [],
  "cssd": [],
  "cheadphone": [],
  "ccarteReseau": [],
  "cmonitor": [],
  "ckeyboard": [],
  "cmouse": [],
  "cmousepad": [],
  "cmousekeys": [],
  "cprinter": [],
  "cnvme": [],
  "cwindows": [],
  "cjeux": [],
  "productpriv": false,
  "specialproduct": false,
  "targetMega": true,
  "targetGiga": true,
  "targetMobile": true,
  "__v": 0
}