{
  "images": [
    {
      "previewImageSrc": "https://apibackend.megapc.tn/uploads/gallerie/webp/1611745876134.webp",
      "thumbnailImageSrc": "https://apibackend.megapc.tn/uploads/gallerie/webp/1611745876134.webp",
      "imgBlur": "data:image/png;base64,iVBORw0KGgoAAAANSUhEUgAAAAQAAAAECAIAAAAmkwkpAAAACXBIWXMAAAPoAAAD6AG1e1JrAAAANUlEQVQImWP4DwYfPrx/8eI5w////7s7Oyf19/3//x/EEeTmYGEAMRj+/vm9edOm2soqIAcA8KkkYaOMfmEAAAAASUVORK5CYII="
    },
    {
      "previewImageSrc": "https://apibackend.megapc.tn/uploads/gallerie/webp/1611745888791.webp",
      "thumbnailImageSrc": "https://apibackend.megapc.tn/uploads/gallerie/webp/1611745888791.webp",
      "imgBlur": "data:image/png;base64,iVBORw0KGgoAAAANSUhEUgAAAAQAAAAECAIAAAAmkwkpAAAACXBIWXMAAAPoAAAD6AG1e1JrAAAAP0lEQVQImQE0AMv/AP///01JSWloYs7NzAD5+fkNBgcgIwBiYl0A+fn4DgQGCQAAfHlTAPr6+RsWGFFNQdzeuXU4FrveaemEAAAAAElFTkSuQmCC"
    },
    {
      "previewImageSrc": "https://apibackend.megapc.tn/uploads/gallerie/webp/1611745860827.webp",
      "thumbnailImageSrc": "https://apibackend.megapc.tn/uploads/gallerie/webp/1611745860827.webp",
      "imgBlur": "data:image/png;base64,iVBORw0KGgoAAAANSUhEUgAAAAQAAAAECAIAAAAmkwkpAAAACXBIWXMAAAPoAAAD6AG1e1JrAAAAOklEQVQImWP49+/fnz+//4MBw/Xr1548eXTo0MGmpmaGmOhIFWVlUREBZgYGhujoyPT01PS01Kb6SgCLRRuG5ulVwgAAAABJRU5ErkJggg=="
    }
  ],
  "_id": "60114a92821a45a8fb5f0107",
  "sku": "sup-xtrfy-xg-c1",
  "mpn": "7340086907996",
  "titleSeo": "Xtrfy XG-C1 Support de cordon de souris Xtrfy.",
  "ratingValue": "4",
  "reviewCount": "38",
  "priceValidUntil": "2022-08-04",
  "referenceInterne": "XG-C1",
  "title": "XTRFY XG-C1",
  "title_fr": "XTRFY XG-C1",
  "description_fr": "<h2>Support XTRFY XG-C1</h2>\n\n<hr />\n<p><span style=\"font-size:22px\">Support de Cordon R&eacute;glable XTRFY C1 Pour Souris Gamer&nbsp;-&nbsp;Solution&nbsp;<strong>rapide et intelligente&nbsp;</strong>-&nbsp;Manipulation facile -&nbsp;Petit mais solide -&nbsp;<strong>Fixez la plaque m&eacute;tallique</strong>&nbsp;&agrave; votre bureau, placez le support de cordon magn&eacute;tique sur la plaque et profitez de mouvements de souris plus fluides - Couleur: Noir</span></p>\n\n<p><img alt=\"XTRFY XG-C1\" src=\"https://api.megapc.tn//uploads/gallerie/1624639403916.webp\" title=\"XTRFY XG-C1\" /></p>\n\n<h3>&nbsp;</h3>\n",
  "miniDescription_fr": "<ul>\n\t<li>Support de cordon de souris r&eacute;glable</li>\n\t<li>Solution rapide et intelligente</li>\n\t<li>Petit mais fort</li>\n\t<li>Manipulation facile</li>\n</ul>\n",
  "notreSelection": true,
  "marque": {
    "_id": "5fcba0924e08349784fa297b",
    "titre": "XTRFY",
    "description": "Xtrfy",
    "__v": 0,
    "urlPhoto": "/uploads/marque/1607180442416.webp",
    "targetGiga": true,
    "targetMega": true,
    "create_date": "2020-12-05T15:00:34.000Z"
  },
  "categorie": {
    "_id": "5e907b1f1c9a7315fc2fc036",
    "order": 5,
    "titre": "ACCESSOIRES",
    "__v": 0,
    "urlPhoto": "/uploads/categorie/1602162264153.jpg",
    "urlPhoto2": "/uploads/categorie/1620205175835.webp",
    "create_date": "2020-04-10T13:56:47.000Z",
    "update_date": "2025-04-28T10:30:39.409Z",
    "visible": true,
    "targetGiga": true,
    "targetMega": true,
    "targetMobile": false
  },
  "filscateg": {
    "children": [],
    "_id": "5ea233bfa4815052c4d1a423",
    "titre": "SOURIS",
    "categorie": "5e907b1f1c9a7315fc2fc036",
    "__v": 0,
    "urlPhoto2": "/uploads/souscateg/1620206287980.webp",
    "order": 1,
    "descriptionSEO": "<p>Souris Pc gamer Tunisie&nbsp;optique Sans fil -&nbsp;Achat Souris Ordinateur bureau, souris Pc portable gaming RGB - Aorus, Razer, Logitech, Corsair, Steelseries</p>",
    "titreSEO": "Souris PC gamer | sans fil pour ordinateur Pc portable | Mega PC",
    "create_date": "2020-04-24T00:33:03.000Z",
    "reference": "SOURIS",
    "update_date": "2021-12-04T08:54:08.545Z",
    "visible": true,
    "targetGiga": true,
    "targetMega": true
  },
  "attributes": [],
  "tag": [],
  "compatibility": [],
  "nFilsCategs": [
    "5ea233bfa4815052c4d1a423"
  ],
  "lien": "XTRFY-XG-C1",
  "gallerie": {
    "_id": "60114841821a45a8fb5f0106",
    "urlPhoto": [
      "/uploads/gallerie/webp/1611745876134.webp",
      "/uploads/gallerie/webp/1611745888791.webp",
      "/uploads/gallerie/webp/1611745860827.webp"
    ],
    "titre": "XTRFY XG-C1",
    "__v": 7,
    "create_date": "2021-01-27T11:02:25.000Z"
  },
  "visibleHorsStock": false,
  "checkStockWhenPurchased": true,
  "visible": true,
  "facilite": false,
  "devis": false,
  "enPromo": false,
  "commande48H": false,
  "enArrivage": false,
  "new": true,
  "vue": 2360,
  "price": 49,
  "tagsSearch": [
    "XTRFY",
    "ACCESSOIRES",
    "SOURIS"
  ],
  "stock": 4,
  "displayForPublic": true,
  "create_date": "2021-01-27T11:12:18.803Z",
  "update_date": "2025-10-22T19:42:01.684Z",
  "ccpu": [],
  "cwebCam": [],
  "cgpu": [],
  "ccase": [],
  "cram": [],
  "ccpuColler": [],
  "cventilateur": [],
  "ccarteMere": [],
  "calim": [],
  "chdd": [],
  "cssd": [],
  "cheadphone": [],
  "ccarteReseau": [],
  "cmonitor": [],
  "ckeyboard": [],
  "cmouse": [],
  "cmousepad": [],
  "cmousekeys": [],
  "cprinter": [],
  "cnvme": [],
  "cwindows": [],
  "cjeux": [],
  "productpriv": false,
  "specialproduct": false,
  "targetMega": true,
  "targetGiga": true,
  "targetMobile": true,
  "__v": 0
}