{
  "images": [
    {
      "previewImageSrc": "https://apibackend.megapc.tn/uploads/gallerie/1686228178192.webp",
      "thumbnailImageSrc": "https://apibackend.megapc.tn/uploads/gallerie/1686228178192.webp",
      "imgBlur": "data:image/png;base64,iVBORw0KGgoAAAANSUhEUgAAAAQAAAAECAIAAAAmkwkpAAAACXBIWXMAAAPoAAAD6AG1e1JrAAAAP0lEQVQImQE0AMv/AP///tDQzsHBwff39wDp5+c/Oz0gHR7V0tQA4+PkHyAlBQADz8zOAPv7+7m5up+eoPDv8Fy/IB8vuS04AAAAAElFTkSuQmCC"
    },
    {
      "previewImageSrc": "https://apibackend.megapc.tn/uploads/gallerie/1686228178213.webp",
      "thumbnailImageSrc": "https://apibackend.megapc.tn/uploads/gallerie/1686228178213.webp",
      "imgBlur": "data:image/png;base64,iVBORw0KGgoAAAANSUhEUgAAAAQAAAAECAIAAAAmkwkpAAAACXBIWXMAAAPoAAAD6AG1e1JrAAAAP0lEQVQImQE0AMv/AP///7KxsbCvr/b29gDb29shICAdGxzAvsAA2NjYFBQTAQAAvLq8APv7+6mpqaCfoPDv8B6lHhYb+506AAAAAElFTkSuQmCC"
    },
    {
      "previewImageSrc": "https://apibackend.megapc.tn/uploads/gallerie/1686228178220.webp",
      "thumbnailImageSrc": "https://apibackend.megapc.tn/uploads/gallerie/1686228178220.webp",
      "imgBlur": "data:image/png;base64,iVBORw0KGgoAAAANSUhEUgAAAAQAAAAECAIAAAAmkwkpAAAACXBIWXMAAAPoAAAD6AG1e1JrAAAAOUlEQVQImWP4////CzD4//8/w48fP3S0dTQ0NN+9ewfiCPALMjGwvH71muH///83bty4evXa3z9/AZxHIvIOz7kbAAAAAElFTkSuQmCC"
    },
    {
      "previewImageSrc": "https://apibackend.megapc.tn/uploads/gallerie/1686228178221.webp",
      "thumbnailImageSrc": "https://apibackend.megapc.tn/uploads/gallerie/1686228178221.webp",
      "imgBlur": "data:image/png;base64,iVBORw0KGgoAAAANSUhEUgAAAAQAAAAECAIAAAAmkwkpAAAACXBIWXMAAAPoAAAD6AG1e1JrAAAAMklEQVQImWP4////2rXrNm/a8v//f4b////LyykYGphAOaKiEgwM7FBOT09fS3MLkAMAYtcgdm75cKoAAAAASUVORK5CYII="
    }
  ],
  "_id": "687ba6da38284c84431e84ef",
  "sku": "ZAWELI-1",
  "mpn": "ZAWELI-1",
  "titleSeo": "PC GAMER ZAWELI 1 | AMD RYZEN 5 3400G | 16GB Ram | 512GB NVMe | MEGA PC | GIGA TECH",
  "desciprtionSeo": "",
  "ratingValue": "4.7",
  "reviewCount": "55",
  "priceValidUntil": "2027-07-09",
  "referenceInterne": "ZAWELI-1",
  "title": "ZAWELI 1 | AMD RYZEN 5 3400G | 16GB Ram | 512GB NVMe",
  "title_fr": "ZAWELI 1 | AMD RYZEN 5 3400G | 16GB Ram | 512GB NVMe",
  "description_fr": "",
  "miniDescription_fr": "<ul>\n\t<li><span style=\"font-size:22px\">🧠 <strong>Processeur</strong> : AMD Ryzen 5 3400G (3.7 GHz / 4.2 GHz)</span></li>\n\t<li><span style=\"font-size:22px\">🧩 <strong>Carte M&egrave;re</strong> : MSI A520M-A PRO</span></li>\n\t<li><span style=\"font-size:22px\">⚡ <strong>RAM</strong> : Silicon Power SP 16GB (2x8GB) 3200MHz</span></li>\n\t<li><span style=\"font-size:22px\">💾 <strong>Stockage</strong> :&nbsp;IMATION X732 NVMe Gen3 512Go</span></li>\n\t<li><span style=\"font-size:22px\">🖤 <strong>Bo&icirc;tier</strong> : Aerocool Hexform</span></li>\n\t<li><span style=\"font-size:22px\">🔋 <strong>Alimentation</strong> : Aerocool LUX 550W 80+ BRONZE</span></li>\n</ul>\n\n<p><span style=\"color:#ff0000\"><span style=\"font-size:22px\">Frais d&#39;installation de Windows : 30 DT</span></span></p>\n",
  "notreSelection": true,
  "marque": {
    "_id": "5fc5ffd20c10517079547a47",
    "titre": "CONFIG PC AMD",
    "description": "CONFIG PC AMD",
    "__v": 0,
    "urlPhoto": "/uploads/marque/1606811608461.webp",
    "targetGiga": true,
    "targetMega": true,
    "create_date": "2020-12-01T08:33:22.000Z"
  },
  "categorie": {
    "_id": "5e907aa91c9a7315fc2fc033",
    "order": 0,
    "titre": "ORDINATEURS",
    "__v": 0,
    "description": "<h1>pc gamer tunisie<br></h1><p>Retrouvez le meilleur <strong>Pc GAMER</strong> en Tunisie sur Megapc.tn . Puissance de calcul, <a href=\"https://megapc.tn/shop/COMPOSANTS/CARTE%20GRAPHIQUE\">carte graphique</a>, ou mémoire vive, sélectionnez le <strong>PC Gaming</strong> adapté à vos besoins.</p><p>Du <strong>PC de bureau</strong> sur mesure à l'ordinateur portable gamer, nos experts alimentent régulièrement les gammes d'ordinateurs en nouveautés pour satisfaire aux exigences des logiciels &amp; derniers jeux Vidéo.</p><p>Trouvez le PC Gamer de vos rêves chez MEGA PC. Config PC Gamer sur mesure; PC Gamer fixe, PC gaming complet!</p>",
    "urlPhoto": "/uploads/categorie/1596623778969.jpg",
    "urlPhoto2": "/uploads/categorie/1620205162725.webp",
    "create_date": "2020-04-10T13:54:49.000Z",
    "update_date": "2024-05-06T12:12:56.357Z",
    "visible": true,
    "targetGiga": true,
    "targetMega": true,
    "targetMobile": true
  },
  "filscateg": {
    "children": [],
    "_id": "5ea23237a4815052c4d1a415",
    "titre": "PC GAMER",
    "categorie": "5e907aa91c9a7315fc2fc033",
    "__v": 0,
    "urlPhoto2": "/uploads/souscateg/1623073866853.webp",
    "order": 0,
    "descriptionSEO": "<p>Achat PC Gamer Tunisie, PC de bureau Gamer sur mesure. Ordinateur Gamer Processeur intel, Ryzen, Carte graphique RTX. Pc gamer tunisie 1000 dt Prix.</p>",
    "titreSEO": "PC Gamer Tunisie - Achat PC Gamer sur mesure - Intel | RYZEN -MEGA PC",
    "create_date": "2020-04-24T00:26:31.000Z",
    "update_date": "2021-12-15T10:41:08.763Z",
    "visible": true,
    "targetGiga": true,
    "targetMega": true
  },
  "attributes": [],
  "tag": [],
  "compatibility": [],
  "nFilsCategs": [
    "5ea23237a4815052c4d1a415",
    "681ce4f0c75bcce7a27d6891"
  ],
  "lien": "ZAWELI-1",
  "gallerie": {
    "_id": "6481ad1ac026d6db8d7dc1c3",
    "titre": "AEROCOOL HEXFORM",
    "urlPhoto": [
      "/uploads/gallerie/1686228178192.webp",
      "/uploads/gallerie/1686228178213.webp",
      "/uploads/gallerie/1686228178220.webp",
      "/uploads/gallerie/1686228178221.webp"
    ],
    "update_date": "2023-06-08T12:42:58.324Z",
    "create_date": "2023-06-08T10:27:38.000Z",
    "__v": 2
  },
  "visibleHorsStock": false,
  "checkStockWhenPurchased": true,
  "visible": true,
  "facilite": false,
  "devis": false,
  "enPromo": false,
  "commande48H": false,
  "enArrivage": false,
  "new": true,
  "vue": 2278,
  "price": 799,
  "tagsSearch": [
    "ORDINATEURS",
    "PC GAMER",
    "BAC_2K25",
    "CONFIG PC AMD"
  ],
  "stock": 99,
  "displayForPublic": true,
  "create_date": "2025-07-03T14:02:32.157Z",
  "update_date": "2025-11-01T12:49:16.866Z",
  "ccpu": [],
  "cwebCam": [],
  "cgpu": [],
  "ccase": [],
  "cram": [],
  "ccpuColler": [],
  "cventilateur": [],
  "ccarteMere": [],
  "calim": [],
  "chdd": [],
  "cssd": [],
  "cheadphone": [],
  "ccarteReseau": [],
  "cmonitor": [],
  "ckeyboard": [],
  "cmouse": [],
  "cmousepad": [],
  "cmousekeys": [],
  "cprinter": [],
  "cnvme": [],
  "cwindows": [],
  "cjeux": [],
  "productpriv": false,
  "specialproduct": false,
  "targetMega": true,
  "targetGiga": true,
  "targetMobile": true,
  "__v": 0
}